MANIFEST.in
README.rst
pyproject.toml
setup.cfg
setup.py
ai/__init__.py
ai/h2o/__init__.py
ai/h2o/sparkling/BackingJar.py
ai/h2o/sparkling/H2ODataFrameConverters.py
ai/h2o/sparkling/Initializer.py
ai/h2o/sparkling/VersionComponents.py
ai/h2o/sparkling/__init__.py
ai/h2o/sparkling/version.txt
ai/h2o/sparkling/ml/__init__.py
ai/h2o/sparkling/ml/metrics/H2OAnomalyMetrics.py
ai/h2o/sparkling/ml/metrics/H2OAutoEncoderMetrics.py
ai/h2o/sparkling/ml/metrics/H2OBinomialGLMMetrics.py
ai/h2o/sparkling/ml/metrics/H2OBinomialMetrics.py
ai/h2o/sparkling/ml/metrics/H2OClusteringMetrics.py
ai/h2o/sparkling/ml/metrics/H2OCommonMetrics.py
ai/h2o/sparkling/ml/metrics/H2OGLRMMetrics.py
ai/h2o/sparkling/ml/metrics/H2OMetricsFactory.py
ai/h2o/sparkling/ml/metrics/H2OMultinomialGLMMetrics.py
ai/h2o/sparkling/ml/metrics/H2OMultinomialMetrics.py
ai/h2o/sparkling/ml/metrics/H2OOrdinalGLMMetrics.py
ai/h2o/sparkling/ml/metrics/H2OOrdinalMetrics.py
ai/h2o/sparkling/ml/metrics/H2OPCAMetrics.py
ai/h2o/sparkling/ml/metrics/H2ORegressionCoxPHMetrics.py
ai/h2o/sparkling/ml/metrics/H2ORegressionGLMMetrics.py
ai/h2o/sparkling/ml/metrics/H2ORegressionMetrics.py
ai/h2o/sparkling/ml/metrics/__init__.py
ai/h2o/sparkling/ml/models/H2OAlgorithmMOJOModelBase.py
ai/h2o/sparkling/ml/models/H2OAutoEncoderMOJOBase.py
ai/h2o/sparkling/ml/models/H2OAutoEncoderMOJOModel.py
ai/h2o/sparkling/ml/models/H2OBinaryModel.py
ai/h2o/sparkling/ml/models/H2OCoxPHMOJOModel.py
ai/h2o/sparkling/ml/models/H2ODRFMOJOModel.py
ai/h2o/sparkling/ml/models/H2ODeepLearningMOJOModel.py
ai/h2o/sparkling/ml/models/H2ODimReductionMOJOModel.py
ai/h2o/sparkling/ml/models/H2OExtendedIsolationForestMOJOModel.py
ai/h2o/sparkling/ml/models/H2OGAMMOJOModel.py
ai/h2o/sparkling/ml/models/H2OGBMMOJOModel.py
ai/h2o/sparkling/ml/models/H2OGLMMOJOModel.py
ai/h2o/sparkling/ml/models/H2OGLRMMOJOBase.py
ai/h2o/sparkling/ml/models/H2OGLRMMOJOModel.py
ai/h2o/sparkling/ml/models/H2OIsolationForestMOJOModel.py
ai/h2o/sparkling/ml/models/H2OKMeansMOJOModel.py
h2o_pysparkling_scoring_2.4.egg-info/PKG-INFO
h2o_pysparkling_scoring_2.4.egg-info/SOURCES.txt
h2o_pysparkling_scoring_2.4.egg-info/dependency_links.txt
h2o_pysparkling_scoring_2.4.egg-info/top_level.txt
